CHANGELOG.md
LICENSE
MANIFEST.in
README.md
pyproject.toml
setup.py
test.py
yescrypthash.c
yescrypthash.h
yescryptmodule.c
yescrypt/sha256.h
yescrypt/sha256_c.h
yescrypt/sysendian.h
yescrypt/yescrypt-best_c.h
yescrypt/yescrypt-opt_c.h
yescrypt/yescrypt-platform_c.h
yescrypt/yescrypt-simd_c.h
yescrypt_hash.egg-info/PKG-INFO
yescrypt_hash.egg-info/SOURCES.txt
yescrypt_hash.egg-info/dependency_links.txt
yescrypt_hash.egg-info/not-zip-safe
yescrypt_hash.egg-info/top_level.txt