Metadata-Version: 2.1
Name: yescrypt-hash
Version: 0.5
Summary: Binding for Yescrypt proof of work hashing.
Requires-Python: >=3.8
License-File: LICENSE
